{
  "data": {
    "_id": 2000,
    "properties": {
      "id": {
        "name": "id",
        "kind": "scalar",
        "primary": true,
        "type": "number",
        "array": false,
        "runtimeType": "number"
      },
      "firstName": {
        "name": "firstName",
        "kind": "scalar",
        "getter": false,
        "setter": false,
        "type": "string",
        "array": false,
        "runtimeType": "string",
        "optional": true
      },
      "lastName": {
        "name": "lastName",
        "kind": "scalar",
        "getter": false,
        "setter": false,
        "type": "string",
        "array": false,
        "runtimeType": "string",
        "optional": true
      },
      "email": {
        "name": "email",
        "kind": "scalar",
        "unique": true,
        "getter": false,
        "setter": false,
        "type": "string",
        "array": false,
        "runtimeType": "string"
      },
      "username": {
        "name": "username",
        "kind": "scalar",
        "unique": true,
        "getter": false,
        "setter": false,
        "type": "string",
        "array": false,
        "runtimeType": "string"
      },
      "password": {
        "name": "password",
        "kind": "scalar",
        "getter": false,
        "setter": false,
        "type": "string",
        "array": false,
        "runtimeType": "string"
      },
      "member": {
        "name": "member",
        "kind": "1:1",
        "cascade": [
          "persist"
        ],
        "owner": false,
        "unique": false,
        "type": "MemberEntity",
        "array": false,
        "runtimeType": "MemberEntity",
        "optional": true
      },
      "createdAt": {
        "name": "createdAt",
        "kind": "scalar",
        "getter": false,
        "setter": false,
        "type": "Date",
        "runtimeType": "Date",
        "array": false
      }
    },
    "primaryKeys": [
      "id"
    ],
    "filters": {},
    "hooks": {},
    "indexes": [],
    "uniques": [],
    "className": "UserEntity",
    "path": "./src/db/entities/UserEntity.ts",
    "name": "UserEntity",
    "abstract": false,
    "internal": true,
    "constructorParams": [],
    "toJsonParams": [],
    "useCache": true,
    "compositePK": false,
    "simplePK": true,
    "collection": "user_entity"
  },
  "origin": "./src/db/entities/UserEntity.ts",
  "hash": "de22388399e6d1c67105d93b9974cf55",
  "version": "6.4.0"
}
